jekkish/__init__.py
jekkish/default.tex
jekkish/jekkish.py
jekkish/tests.py
jekkish/texhelpers.py
jekkish-0.2.0.2.dist-info/.DS_Store
jekkish-0.2.0.2.dist-info/DESCRIPTION.rst
jekkish-0.2.0.2.dist-info/entry_points.txt
jekkish-0.2.0.2.dist-info/METADATA
jekkish-0.2.0.2.dist-info/metadata.json
jekkish-0.2.0.2.dist-info/RECORD
jekkish-0.2.0.2.dist-info/top_level.txt
jekkish-0.2.0.2.dist-info/WHEEL
