Metadata-Version: 2.0
Name: jekkish
Version: 0.2.0.2
Summary: A CLI frontend for pdftex for easy templated LaTeX writing.
Home-page: https://github.com/joshjzaslow/latex-jekkish
Author: Josh Zaslow
Author-email: josh.zaslow@gmail.com
License: MIT
Download-URL: https://github.com/joshjzaslow/latex-jekkish/tarball/0.2
Keywords: LaTeX
Platform: UNKNOWN
Classifier: Development Status :: 3 - Alpha
Classifier: License :: OSI Approved :: MIT License
Classifier: Operating System :: POSIX :: Linux
Classifier: Operating System :: Microsoft :: Windows
Classifier: Operating System :: MacOS
Classifier: Programming Language :: Python
Classifier: Programming Language :: Python :: 2.7
Classifier: Programming Language :: Python :: 3.4
Classifier: Topic :: Text Processing
Classifier: Topic :: Text Processing :: Markup :: LaTeX
Requires: PyYAML
Requires: Jinja2
Requires-Dist: PyYAML
Requires-Dist: Jinja2
